Metadata-Version: 2.1
Name: xtrm-drest
Version: 0.0.10
Summary: Dynamic REST with DRF Writable Nested package for CRUD
Home-page: 
Author: Extreme Solutions
Author-email: ketan@extremesolutions.in
Classifier: Programming Language :: Python :: 3
Classifier: License :: OSI Approved :: MIT License
Classifier: Operating System :: OS Independent
Requires-Python: >=3.6
License-File: LICENSE.md
License-File: LICENSE.txt
